lika/__init__.py
lika/response.py
lika/router.py
lika/server.py
lika-0.2.0.dist-info/LICENSE
lika-0.2.0.dist-info/METADATA
lika-0.2.0.dist-info/WHEEL
lika-0.2.0.dist-info/RECORD
