Metadata-Version: 2.1
Name: lika
Version: 0.2.0
Summary: 
Author: KarisAya
Author-email: 1048827424@qq.com
Requires-Python: >=3.12,<4.0
Classifier: Programming Language :: Python :: 3
